huaweicloudsdkprojectman/__init__.py
huaweicloudsdkprojectman/v4/__init__.py
huaweicloudsdkprojectman/v4/projectman_async_client.py
huaweicloudsdkprojectman/v4/projectman_client.py
huaweicloudsdkprojectman/v4/model/__init__.py
huaweicloudsdkprojectman/v4/model/add_apply_join_project_for_agc_request.py
huaweicloudsdkprojectman/v4/model/add_apply_join_project_for_agc_response.py
huaweicloudsdkprojectman/v4/model/add_issue_work_hours_request.py
huaweicloudsdkprojectman/v4/model/add_issue_work_hours_request_body.py
huaweicloudsdkprojectman/v4/model/add_issue_work_hours_response.py
huaweicloudsdkprojectman/v4/model/add_issue_work_hours_response_body_added_work_hours.py
huaweicloudsdkprojectman/v4/model/add_member_request_v4.py
huaweicloudsdkprojectman/v4/model/add_member_v4_request.py
huaweicloudsdkprojectman/v4/model/add_member_v4_response.py
huaweicloudsdkprojectman/v4/model/associate_issue_detail.py
huaweicloudsdkprojectman/v4/model/associated_test_case.py
huaweicloudsdkprojectman/v4/model/attach_wiki_detail.py
huaweicloudsdkprojectman/v4/model/attachment_entity.py
huaweicloudsdkprojectman/v4/model/attachment_vo.py
huaweicloudsdkprojectman/v4/model/batch_add_member_request_v4.py
huaweicloudsdkprojectman/v4/model/batch_add_members_v4_request.py
huaweicloudsdkprojectman/v4/model/batch_add_members_v4_request_body.py
huaweicloudsdkprojectman/v4/model/batch_add_members_v4_response.py
huaweicloudsdkprojectman/v4/model/batch_associated_issue.py
huaweicloudsdkprojectman/v4/model/batch_delelte_issues_request_v4.py
huaweicloudsdkprojectman/v4/model/batch_delete_issues_v4_request.py
huaweicloudsdkprojectman/v4/model/batch_delete_issues_v4_response.py
huaweicloudsdkprojectman/v4/model/batch_delete_iterations_v4_request.py
huaweicloudsdkprojectman/v4/model/batch_delete_iterations_v4_request_body.py
huaweicloudsdkprojectman/v4/model/batch_delete_iterations_v4_response.py
huaweicloudsdkprojectman/v4/model/batch_delete_members_v4_request.py
huaweicloudsdkprojectman-3.1.184.dist-info/METADATA
huaweicloudsdkprojectman-3.1.184.dist-info/WHEEL
huaweicloudsdkprojectman-3.1.184.dist-info/licenses/LICENSE
huaweicloudsdkprojectman-3.1.184.dist-info/RECORD
